odoo/addons/base_rest_auth_api_key/README.rst
odoo/addons/base_rest_auth_api_key/__init__.py
odoo/addons/base_rest_auth_api_key/__manifest__.py
odoo/addons/base_rest_auth_api_key/apispec/__init__.py
odoo/addons/base_rest_auth_api_key/apispec/rest_method_security_plugin.py
odoo/addons/base_rest_auth_api_key/components/__init__.py
odoo/addons/base_rest_auth_api_key/components/service.py
odoo/addons/base_rest_auth_api_key/i18n/base_rest_auth_api_key.pot
odoo/addons/base_rest_auth_api_key/readme/CONTRIBUTORS.rst
odoo/addons/base_rest_auth_api_key/readme/DESCRIPTION.rst
odoo/addons/base_rest_auth_api_key/static/description/icon.png
odoo/addons/base_rest_auth_api_key/static/description/index.html
odoo14_addon_base_rest_auth_api_key-14.0.1.0.2.dist-info/METADATA
odoo14_addon_base_rest_auth_api_key-14.0.1.0.2.dist-info/WHEEL
odoo14_addon_base_rest_auth_api_key-14.0.1.0.2.dist-info/top_level.txt
odoo14_addon_base_rest_auth_api_key-14.0.1.0.2.dist-info/RECORD
